{
  "_class": "symbolInstance",
  "do_objectID": "AAD06044-2557-4AA0-BE04-1F11A49EDA1E",
  "exportOptions": {
    "_class": "exportOptions",
    "exportFormats": [
    ],
    "includedLayerIds": [
    ],
    "layerOptions": 0,
    "shouldTrim": false
  },
  "frame": {
    "_class": "rect",
    "constrainProportions": false,
    "height": 798,
    "width": 361,
    "x": 300,
    "y": 307
  },
  "horizontalSpacing": 0,
  "isFlippedHorizontal": false,
  "isFlippedVertical": false,
  "isLocked": false,
  "isVisible": true,
  "layerListExpandedType": 0,
  "masterInfluenceEdgeMaxXPadding": 1,
  "masterInfluenceEdgeMaxYPadding": 1,
  "masterInfluenceEdgeMinXPadding": 1,
  "masterInfluenceEdgeMinYPadding": 1,
  "name": "Map",
  "nameIsFixed": false,
  "originalObjectID": "165A8232-9627-4EC6-BB46-A5C054FDCDA9",
  "overrides": {
    "F2D49A8E-3AB9-443B-946B-003A849D51B4": {
      "symbolID": "7A0DB581-03EB-4193-8CDE-C22059D55DED"
    }
  },
  "resizingConstraint": 63,
  "resizingType": 0,
  "rotation": 0,
  "shouldBreakMaskChain": false,
  "style": {
    "_class": "style",
    "endDecorationType": 0,
    "miterLimit": 10,
    "startDecorationType": 0
  },
  "symbolID": "3F9E8849-5C9C-43D3-9BBE-F393BF21DAF8",
  "userInfo": {
    "com.animaapp.stc-sketch-plugin": {
      "kModelPropertiesKey": {
        "actions": [
          {
            "animation": 0,
            "customAnimationId": "",
            "delayFromTrigger": 0,
            "modelID": "OpenScreen_41239a27-6e9f-46bb-8a8c-d18ec1de9c89",
            "model_class": "ADModelActionPresentScreen",
            "model_version": 0.1,
            "name": "untitled",
            "presentationType": 2,
            "screenId": "DD78E700-7342-4503-B4EA-E656AECED353",
            "trigger": 4
          }
        ]
      }
    },
    "com.invision.prototype": {
      "backgroundOpacity": 0,
      "closeOnClickOutside": 1,
      "componentType": "SRLink",
      "fixOverlayPosition": 1,
      "gesture": 0,
      "linkType": 0,
      "maintainScrollPositionAfterGesture": 0,
      "maintainScrollPositionAfterRedirect": 0,
      "openURLInNewWindow": 0,
      "overlayPosition": 0,
      "overlayTransition": 0,
      "redirectAfter": 0,
      "reverseTransitionOnClose": 1,
      "scrollToPosition": 0,
      "smoothScrolling": 0,
      "stayOnTargetScreen": 0,
      "targetArtboardID": "DD78E700-7342-4503-B4EA-E656AECED353",
      "transition": 0
    }
  },
  "verticalSpacing": 0
}