{
  "_class": "group",
  "do_objectID": "52A7ED36-A95D-46A4-BC7D-23240563E2E4",
  "exportOptions": {
    "_class": "exportOptions",
    "exportFormats": [
    ],
    "includedLayerIds": [
    ],
    "layerOptions": 0,
    "shouldTrim": false
  },
  "frame": {
    "_class": "rect",
    "constrainProportions": false,
    "height": 15,
    "width": 95,
    "x": 119,
    "y": 21
  },
  "hasClickThrough": false,
  "isFlippedHorizontal": false,
  "isFlippedVertical": false,
  "isLocked": false,
  "isVisible": true,
  "layerListExpandedType": 0,
  "layers": [
    {
      "class": "text",
      "id": "A50D9C42-80FF-44F0-8EBE-97BD7B9BD2A1"
    },
    {
      "class": "shapeGroup",
      "id": "BFA16DDE-96B6-4F01-8858-C4C746F101DC"
    }
  ],
  "name": "Group 15",
  "nameIsFixed": false,
  "resizingConstraint": 63,
  "resizingType": 0,
  "rotation": 0,
  "shouldBreakMaskChain": false,
  "style": {
    "_class": "style",
    "endDecorationType": 0,
    "miterLimit": 10,
    "startDecorationType": 0
  },
  "userInfo": {
    "com.animaapp.stc-sketch-plugin": {
      "kModelPropertiesKey": {
      }
    }
  }
}