{
  "_class": "symbolInstance",
  "do_objectID": "0AF79A2F-884A-476C-89FC-D4A691D18EAD",
  "exportOptions": {
    "_class": "exportOptions",
    "exportFormats": [
    ],
    "includedLayerIds": [
    ],
    "layerOptions": 0,
    "shouldTrim": false
  },
  "frame": {
    "_class": "rect",
    "constrainProportions": false,
    "height": 25,
    "width": 112,
    "x": 37,
    "y": 137
  },
  "horizontalSpacing": 0,
  "isFlippedHorizontal": false,
  "isFlippedVertical": false,
  "isLocked": false,
  "isVisible": true,
  "layerListExpandedType": 0,
  "masterInfluenceEdgeMaxXPadding": 1,
  "masterInfluenceEdgeMaxYPadding": 1,
  "masterInfluenceEdgeMinXPadding": 1,
  "masterInfluenceEdgeMinYPadding": 1,
  "name": "Call to Action",
  "nameIsFixed": true,
  "originalObjectID": "0AF79A2F-884A-476C-89FC-D4A691D18EAD",
  "overrides": {
    "8B1AE573-82BF-42E3-A929-FC16E0417F91": "Conocé Más"
  },
  "resizingConstraint": 63,
  "resizingType": 0,
  "rotation": 0,
  "shouldBreakMaskChain": false,
  "style": {
    "_class": "style",
    "endDecorationType": 0,
    "miterLimit": 10,
    "startDecorationType": 0
  },
  "symbolID": "704071D3-8EEA-4BC6-B758-FB8077278E50",
  "userInfo": {
    "com.animaapp.stc-sketch-plugin": {
      "kModelPropertiesKey": {
      }
    }
  },
  "verticalSpacing": 0
}